<?xml version="1.0" encoding="UTF-8"?>
<tiles>
  <tileSize>256</tileSize>
  <originalWidth>9934</originalWidth>
  <originalHeight>7017</originalHeight>
  <maxZoom>6</maxZoom>
  <generatedAt>2026-05-20T21:51:28.934Z</generatedAt>
  <levels>
    <level>
      <z>0</z>
      <width>156</width>
      <height>110</height>
      <cols>1</cols>
      <rows>1</rows>
      <tiles>1</tiles>
    </level>
    <level>
      <z>1</z>
      <width>311</width>
      <height>220</height>
      <cols>2</cols>
      <rows>1</rows>
      <tiles>2</tiles>
    </level>
    <level>
      <z>2</z>
      <width>621</width>
      <height>439</height>
      <cols>3</cols>
      <rows>2</rows>
      <tiles>6</tiles>
    </level>
    <level>
      <z>3</z>
      <width>1242</width>
      <height>878</height>
      <cols>5</cols>
      <rows>4</rows>
      <tiles>20</tiles>
    </level>
    <level>
      <z>4</z>
      <width>2484</width>
      <height>1755</height>
      <cols>10</cols>
      <rows>7</rows>
      <tiles>70</tiles>
    </level>
    <level>
      <z>5</z>
      <width>4967</width>
      <height>3509</height>
      <cols>20</cols>
      <rows>14</rows>
      <tiles>280</tiles>
    </level>
    <level>
      <z>6</z>
      <width>9934</width>
      <height>7017</height>
      <cols>39</cols>
      <rows>28</rows>
      <tiles>1092</tiles>
    </level>
  </levels>
</tiles>